Metadata-Version: 2.1
Name: snipgenie
Version: 0.7.0
Summary: variant calling and phylogenies from microbial WGS data
Home-page: https://github.com/dmnfarrell/snipgenie
Author: Damien Farrell
Author-email: farrell.damien@gmail.com
License: GPL v3
Keywords: bioinformatics,biology,genomics
Classifier: Operating System :: OS Independent
Classifier: Programming Language :: Python :: 2.7
Classifier: Programming Language :: Python :: 3.7
Classifier: Operating System :: MacOS :: MacOS X
Classifier: Operating System :: Microsoft :: Windows
Classifier: Operating System :: POSIX
Classifier: License :: OSI Approved :: GNU General Public License v3 (GPLv3)
Classifier: Development Status :: 4 - Beta
Classifier: Intended Audience :: Science/Research
Classifier: Topic :: Scientific/Engineering :: Bio-Informatics
Requires-Dist: numpy>=1.2
Requires-Dist: pandas>=0.24
Requires-Dist: matplotlib>=3.0
Requires-Dist: biopython==1.84
Requires-Dist: pyvcf3
Requires-Dist: pyfaidx
Requires-Dist: bcbio_gff
Requires-Dist: tqdm
